fluvius_energy_service_company/__init__.py
fluvius_energy_service_company/fluvius_authentication.py
fluvius_energy_service_company/fluvius_config.py
fluvius_energy_service_company/data_objects/FluviusAuthenticationToken.py
fluvius_energy_service_company/data_objects/FluviusData.py
fluvius_energy_service_company/data_objects/FluviusDataResponse.py
fluvius_energy_service_company/data_objects/FluviusElectricityMeter.py
fluvius_energy_service_company/data_objects/FluviusMandate.py
fluvius_energy_service_company/data_objects/FluviusMandateEnergy.py
fluvius_energy_service_company/data_objects/FluviusMeasurement.py
fluvius_energy_service_company/data_objects/FluviusQuarterHourlyEnergy.py
fluvius_energy_service_company/data_objects/__init__.py
fluvius_energy_service_company/v2/__init__.py
fluvius_energy_service_company/v2/energy_service_company.py
tests/__init__.py
fluvius_energy_service_company-0.1.dist-info/LICENSE
fluvius_energy_service_company-0.1.dist-info/METADATA
fluvius_energy_service_company-0.1.dist-info/WHEEL
fluvius_energy_service_company-0.1.dist-info/top_level.txt
fluvius_energy_service_company-0.1.dist-info/RECORD
