Metadata-Version: 2.1
Name: fluvius-energy-service-company
Version: 0.1
Summary: Wrapper for the Fluvius energy service company API that you can use as an "Energie dienstverlener".
Home-page: https://github.com/VONKT/fluvius-energy-service-company
Author: Ward Schodts
Author-email: ward@vonkt.energy
License: GNU LESSER GENERAL PUBLIC LICENSE
License-File: LICENSE
Requires-Dist: PyJWT ==2.8.0
